axsqlalchemy/__init__.py
axsqlalchemy/model.py
axsqlalchemy/schema.py
axsqlalchemy/settings.py
axsqlalchemy/repository/__init__.py
axsqlalchemy/repository/adder.py
axsqlalchemy/repository/all_getter.py
axsqlalchemy/repository/base.py
axsqlalchemy/repository/common.py
axsqlalchemy/repository/deleter.py
axsqlalchemy/repository/getter.py
axsqlalchemy/repository/paginated.py
axsqlalchemy/repository/paginated_all_getter.py
axsqlalchemy/repository/status_updater.py
axsqlalchemy/repository/types.py
axsqlalchemy/repository/updateter.py
axsqlalchemy/testing/__init__.py
axsqlalchemy/testing/base_async_repo_test.py
axsqlalchemy/utils/__init__.py
axsqlalchemy/utils/creation.py
axsqlalchemy/utils/filters.py
axsqlalchemy-0.0.69.dist-info/METADATA
axsqlalchemy-0.0.69.dist-info/WHEEL
axsqlalchemy-0.0.69.dist-info/top_level.txt
axsqlalchemy-0.0.69.dist-info/RECORD
