Metadata-Version: 2.1
Name: axsqlalchemy
Version: 0.0.69
Summary: SQLAlchemy-based library that allows you to implement a uow pattern based on this library
Author: axdjuraev
Author-email: <axdjuraev@gmail.com>
Requires-Dist: uuid >=1.30
Requires-Dist: axabc >=0.0.1
Requires-Dist: SQLAlchemy ==2.0.3
